jimiko/_jimiko_wrapper.cpython-310-manylinux2014_x86_64.so
jimiko/_jimikosftp_wrapper.cpython-312-darwin.so
jimiko/_jimiko_wrapper.cpython-313-darwin.so
jimiko/_jimikosftp_wrapper.cpython-313-manylinux2014_x86_64.so
jimiko/_jimikosftp_wrapper.cpython-310-manylinux2014_x86_64.so
jimiko/_jimikosftp_wrapper.cpython-313-darwin.so
jimiko/_jimiko_wrapper.cpython-312-darwin.so
jimiko/_jimiko_wrapper.cpython-313-manylinux2014_x86_64.so
jimiko/_jimikosftp_wrapper.cpython-312-manylinux2014_x86_64.so
jimiko/_jimikosftp_wrapper.cpython-39-manylinux2014_x86_64.so
jimiko/_jimiko_wrapper.cpython-311-manylinux2014_x86_64.so
jimiko/_jimiko_wrapper.cpython-39-manylinux2014_x86_64.so
jimiko/_jimiko_wrapper.cpython-312-manylinux2014_x86_64.so
jimiko/_jimikosftp_wrapper.cpython-311-manylinux2014_x86_64.so
jimiko/__init__.py
jimiko-2.0.17rc1.dist-info/LICENSE
jimiko-2.0.17rc1.dist-info/licenses/LICENSE
jimiko-2.0.17rc1.dist-info/WHEEL
jimiko-2.0.17rc1.dist-info/METADATA
jimiko-2.0.17rc1.dist-info/RECORD
