Metadata-Version: 2.4
Name: jimiko
Version: 2.0.17rc1
Summary: High-performance SSH and SFTP client for network automation
Author: Jimiko Team
Author-email: James Hill <jmhill2@gmail.com>
License: MIT
Keywords: ssh,networking,automation,libssh2,openssl,paramiko,netmiko
Classifier: Development Status :: 3 - Alpha
Classifier: Intended Audience :: Developers
Classifier: Intended Audience :: System Administrators
Classifier: License :: OSI Approved :: MIT License
Classifier: Programming Language :: Python :: 3.9
Classifier: Programming Language :: Python :: 3.10
Classifier: Programming Language :: Python :: 3.11
Classifier: Programming Language :: Python :: 3.12
Classifier: Programming Language :: Python :: 3.13
Classifier: Operating System :: POSIX :: Linux
Classifier: Operating System :: MacOS :: MacOS X
Classifier: Topic :: System :: Networking
Requires-Python: >=3.9
License-File: LICENSE
Provides-Extra: test
Requires-Dist: pytest>=7.0.0; extra == "test"
Dynamic: author
Dynamic: license-file
Dynamic: requires-python
